scranpy/_run_tsne.py
scranpy/_utils_se.py
scranpy/_summarize_effects.py
scranpy/_run_pca.py
scranpy/_score_gene_set.py
scranpy/_se_get_test_data.py
scranpy/_se_run_umap.py
scranpy/_aggregate_across_genes.py
scranpy/_model_gene_variances.py
scranpy/_se_cluster_graph.py
scranpy/_rna_quality_control.py
scranpy/_se_run_all_neighbor_steps.py
scranpy/_se_run_tsne.py
scranpy/_se_run_pca.py
scranpy/_adt_quality_control.py
scranpy/_aggregate_across_cells.py
scranpy/__init__.py
scranpy/_se_quick_adt_qc.py
scranpy/_subsample_by_neighbors.py
scranpy/_cluster_kmeans.py
scranpy/_choose_highly_variable_genes.py
scranpy/_fit_variance_trend.py
scranpy/_se_score_markers.py
scranpy/_run_umap.py
scranpy/_utils_neighbors.py
scranpy/_se_quick_rna_qc.py
scranpy/_normalize_counts.py
scranpy/_combine_factors.py
scranpy/_se_normalize_rna_counts.py
scranpy/_se_quick_crispr_qc.py
scranpy/_se_aggregate_across_genes.py
scranpy/_cluster_graph.py
scranpy/_score_markers.py
scranpy/_se_cluster_kmeans.py
scranpy/_utils_general.py
scranpy/_se_choose_rna_hvgs.py
scranpy/_se_analyze.py
scranpy/_compute_clrm1_factors.py
scranpy/_lib_scranpy.cpython-312-darwin.so
scranpy/_se_normalize_adt_counts.py
scranpy/_utils_qc.py
scranpy/_scale_by_neighbors.py
scranpy/_test_enrichment.py
scranpy/_build_snn_graph.py
scranpy/_se_correct_mnn.py
scranpy/_crispr_quality_control.py
scranpy/_se_normalize_crispr_counts.py
scranpy/_se_scale_by_neighbors.py
scranpy/_analyze.py
scranpy/_center_size_factors.py
scranpy/_correct_mnn.py
scranpy/_choose_pseudo_count.py
scranpy/_run_all_neighbor_steps.py
scranpy/_se_aggregate_across_cells.py
scranpy/_se_score_gene_set.py
scranpy/_sanitize_size_factors.py
scranpy-0.3.0.dist-info/RECORD
scranpy-0.3.0.dist-info/WHEEL
scranpy-0.3.0.dist-info/top_level.txt
scranpy-0.3.0.dist-info/METADATA
scranpy-0.3.0.dist-info/licenses/LICENSE.txt
