Metadata-Version: 2.4
Name: scranpy
Version: 0.3.0
Summary: Analyze multi-modal single-cell data!
Home-page: https://github.com/libscran/scranpy
Author: "Jayaram Kancherla, Aaron Lun"
Author-email: jayaram.kancherla@gmail.com
License: MIT
Project-URL: Documentation, https://github.com/libscran/scranpy
Platform: any
Classifier: Development Status :: 4 - Beta
Classifier: Programming Language :: Python
Requires-Python: >=3.9
License-File: LICENSE.txt
Requires-Dist: importlib-metadata; python_version < "3.8"
Requires-Dist: mattress>=0.4.1
Requires-Dist: knncolle>=0.3.0
Requires-Dist: numpy
Requires-Dist: biocutils>=0.2.1
Requires-Dist: biocframe>=0.6.2
Requires-Dist: delayedarray
Provides-Extra: optional
Requires-Dist: singlecellexperiment; extra == "optional"
Requires-Dist: summarizedexperiment; extra == "optional"
Requires-Dist: scrnaseq; extra == "optional"
Requires-Dist: scipy; extra == "optional"
Provides-Extra: testing
Requires-Dist: setuptools; extra == "testing"
Requires-Dist: pytest; extra == "testing"
Requires-Dist: pytest-cov; extra == "testing"
Requires-Dist: singlecellexperiment>=0.6.0; extra == "testing"
Requires-Dist: summarizedexperiment>=0.6.3; extra == "testing"
Requires-Dist: scrnaseq>=0.3.1; extra == "testing"
Requires-Dist: scipy; extra == "testing"
Dynamic: license-file
